alpaca/Pairs_Trading_Algo_Example.py
alpaca/__init__.py
alpaca/test.py
charts/ChartLabels.py
charts/DashChart.py
charts/FeaturesChart.py
charts/PricesChart.py
charts/__init__.py
charts/streaming.py
model/AutoArimaModel.py
model/BaselineModel.py
model/FeatureEngineer.py
model/Features.py
model/KNeighborsModel.py
model/LSTMModel.py
model/LinearRegressionModel.py
model/Price.py
model/ProphetModel.py
model/__init__.py
polygon/__init__.py
utils/AlphaVantageUtils.py
utils/Config.py
utils/FeaturesUpdater.py
utils/ModelUtils.py
utils/PostgresUtils.py
utils/PriceUpdater.py
utils/__init__.py
ga_capstone_hakngrow-0.0.18.dist-info/LICENSE
ga_capstone_hakngrow-0.0.18.dist-info/METADATA
ga_capstone_hakngrow-0.0.18.dist-info/WHEEL
ga_capstone_hakngrow-0.0.18.dist-info/top_level.txt
ga_capstone_hakngrow-0.0.18.dist-info/RECORD
