Metadata-Version: 2.1
Name: ga-capstone-hakngrow
Version: 0.0.18
Summary: GA Capstone project
Home-page: https://github.com/hakngrow/capstone.git
Author: Howie Ng
Author-email: hakngrow@gmail.com
License: UNKNOWN
Platform: UNKNOWN
Classifier: Programming Language :: Python :: 3
Classifier: License :: OSI Approved :: MIT License
Classifier: Operating System :: OS Independent
Requires-Python: >=3.5
